Metadata-Version: 1.1
Name: persona-idp
Version: 0.9
Summary: This is a generic and reusable python implementation of Mozilla Persona Identity Provider <https://developer.mozilla.org/en-US/Persona/Identity_Provider_Overview>.
Home-page: https://github.com/dpaw2/persona-idp
Author: Tomas Krajca
Author-email: tomas.krajca@DPaW.wa.gov.au
License: BSD License
Keywords: persona identity provider IDP mozilla dpaw single-sign-on authentication
Platform: UNKNOWN
Classifier: Development Status :: 4 - Beta
Classifier: Environment :: Web Environment
Classifier: Environment :: Web Environment :: Mozilla
Classifier: License :: OSI Approved :: BSD License
Classifier: Programming Language :: Python
Classifier: Programming Language :: Python :: 2
Classifier: Programming Language :: Python :: 3
Classifier: Topic :: Internet :: WWW/HTTP :: WSGI
Classifier: Topic :: Internet :: WWW/HTTP :: WSGI :: Application
